dm_aioinfluxdb/__init__.py
dm_aioinfluxdb/aioinfluxdb_client.py
dm_aioinfluxdb-0.2.5.dist-info/METADATA
dm_aioinfluxdb-0.2.5.dist-info/WHEEL
dm_aioinfluxdb-0.2.5.dist-info/top_level.txt
dm_aioinfluxdb-0.2.5.dist-info/RECORD
