Metadata-Version: 2.1
Name: dm-aioinfluxdb
Version: 0.2.5
Summary: This is my custom aioinfluxdb client
Home-page: https://pypi.org/project/dm-aioinfluxdb
Author: dimka4621
Author-email: mismartconfig@gmail.com
Project-URL: GitHub, https://github.com/DIMKA4621/dm-aioinfluxdb
Keywords: dm aioinfluxdb
Classifier: Programming Language :: Python :: 3.8
Classifier: License :: OSI Approved :: MIT License
Classifier: Operating System :: OS Independent
Requires-Python: >=3.8
Requires-Dist: aiohttp ==3.9.2
Requires-Dist: aiocsv ==1.2.5
Requires-Dist: dm-logger ==0.5.2
Requires-Dist: influxdb-client ==1.39.0
